jsonlogging/__init__.py
jsonlogging/config.py
jsonlogging/handlers.py
jsonlogging-0.190701.dist-info/METADATA
jsonlogging-0.190701.dist-info/WHEEL
jsonlogging-0.190701.dist-info/top_level.txt
jsonlogging-0.190701.dist-info/RECORD
