Metadata-Version: 2.1
Name: jsonlogging
Version: 0.190701
Summary: json formatted log
Home-page: https://www.baidu.com
Author: yupeng.ma
Author-email: yupeng.ma@ucar.com
License: MIT License
Keywords: json logging
Platform: any
